{
  "generatedAt": "2026-03-12T06:58:42.152Z",
  "brand": "recipedia",
  "assortmentCode": "BF8813",
  "feedUrl": "https://www.receptmuhely.hu/home.productfeed.json",
  "totalProblematicPages": 42,
  "problematicPages": [
    {
      "type": "problematic",
      "brand": "recipedia",
      "assortmentCode": "BF8813",
      "feedUrl": "https://www.receptmuhely.hu/home.productfeed.json",
      "url": "https://www.receptmuhely.hu/p/hellmanns-mustar--szosz.html/08712566388677",
      "gtin": "08712566388677",
      "checkedAt": "2026-03-12T06:53:53.376Z"
    },
    {
      "type": "problematic",
      "brand": "recipedia",
      "assortmentCode": "BF8813",
      "feedUrl": "https://www.receptmuhely.hu/home.productfeed.json",
      "url": "https://www.receptmuhely.hu/p/hellmanns-real-majonez.html/08714100848234",
      "gtin": "08714100848234",
      "checkedAt": "2026-03-12T06:58:41.521Z"
    },
    {
      "type": "problematic",
      "brand": "recipedia",
      "assortmentCode": "BF8813",
      "feedUrl": "https://www.receptmuhely.hu/home.productfeed.json",
      "url": "https://www.receptmuhely.hu/p/hellmanns-light-majonez.html/08714100848623",
      "gtin": "08714100848623",
      "checkedAt": "2026-03-12T06:58:41.523Z"
    },
    {
      "type": "problematic",
      "brand": "recipedia",
      "assortmentCode": "BF8813",
      "feedUrl": "https://www.receptmuhely.hu/home.productfeed.json",
      "url": "https://www.receptmuhely.hu/p/hellmanns-avokados-szosz.html/08720182308078",
      "gtin": "08720182308078",
      "checkedAt": "2026-03-12T06:52:59.039Z"
    },
    {
      "type": "problematic",
      "brand": "recipedia",
      "assortmentCode": "BF8813",
      "feedUrl": "https://www.receptmuhely.hu/home.productfeed.json",
      "url": "https://www.receptmuhely.hu/p/hellmanns-tzatziki-jellegu-szosz.html/08720182589699",
      "gtin": "08720182589699",
      "checkedAt": "2026-03-12T06:58:41.738Z"
    },
    {
      "type": "problematic",
      "brand": "recipedia",
      "assortmentCode": "BF8813",
      "feedUrl": "https://www.receptmuhely.hu/home.productfeed.json",
      "url": "https://www.receptmuhely.hu/p/hellmanns-fokhagymas-szosz.html/08720182817730",
      "gtin": "08720182817730",
      "checkedAt": "2026-03-12T06:58:41.747Z"
    },
    {
      "type": "problematic",
      "brand": "recipedia",
      "assortmentCode": "BF8813",
      "feedUrl": "https://www.receptmuhely.hu/home.productfeed.json",
      "url": "https://www.receptmuhely.hu/p/hellmanns-extra-chili-szosz.html/08720182822567",
      "gtin": "08720182822567",
      "checkedAt": "2026-03-12T06:53:38.627Z"
    },
    {
      "type": "problematic",
      "brand": "recipedia",
      "assortmentCode": "BF8813",
      "feedUrl": "https://www.receptmuhely.hu/home.productfeed.json",
      "url": "https://www.receptmuhely.hu/p/hellmanns-vegan-majonez.html/08721201906305",
      "gtin": "08721201906305",
      "checkedAt": "2026-03-12T06:54:43.067Z"
    },
    {
      "type": "problematic",
      "brand": "recipedia",
      "assortmentCode": "BF8813",
      "feedUrl": "https://www.receptmuhely.hu/home.productfeed.json",
      "url": "https://www.receptmuhely.hu/p/knorr-tesztas-keszetel-tejszines-zoldseges.html/08721201920295",
      "gtin": "08721201920295",
      "checkedAt": "2026-03-12T06:53:01.500Z"
    },
    {
      "type": "problematic",
      "brand": "recipedia",
      "assortmentCode": "BF8813",
      "feedUrl": "https://www.receptmuhely.hu/home.productfeed.json",
      "url": "https://www.receptmuhely.hu/p/knorr-tesztas-keszetel-kremes-sajtszoszos.html/08721201921599",
      "gtin": "08721201921599",
      "checkedAt": "2026-03-12T06:54:00.784Z"
    },
    {
      "type": "problematic",
      "brand": "recipedia",
      "assortmentCode": "BF8813",
      "feedUrl": "https://www.receptmuhely.hu/home.productfeed.json",
      "url": "https://www.receptmuhely.hu/p/knorr-snack-teszta-kebab-izesitessel.html/08721201974014",
      "gtin": "08721201974014",
      "checkedAt": "2026-03-12T06:58:41.523Z"
    },
    {
      "type": "problematic",
      "brand": "recipedia",
      "assortmentCode": "BF8813",
      "feedUrl": "https://www.receptmuhely.hu/home.productfeed.json",
      "url": "https://www.receptmuhely.hu/p/hellmanns-majonez-tasty.html/08721317715624",
      "gtin": "08721317715624",
      "checkedAt": "2026-03-12T06:58:41.524Z"
    },
    {
      "type": "problematic",
      "brand": "recipedia",
      "assortmentCode": "BF8813",
      "feedUrl": "https://www.receptmuhely.hu/home.productfeed.json",
      "url": "https://www.receptmuhely.hu/p/delikat-etelizesito-75g.html/05996358010554",
      "gtin": "05996358010554",
      "checkedAt": "2026-03-12T06:58:41.524Z"
    },
    {
      "type": "problematic",
      "brand": "recipedia",
      "assortmentCode": "BF8813",
      "feedUrl": "https://www.receptmuhely.hu/home.productfeed.json",
      "url": "https://www.receptmuhely.hu/p/delikat-etelizesito-250g.html/05996358010561",
      "gtin": "05996358010561",
      "checkedAt": "2026-03-12T06:54:20.677Z"
    },
    {
      "type": "problematic",
      "brand": "recipedia",
      "assortmentCode": "BF8813",
      "feedUrl": "https://www.receptmuhely.hu/home.productfeed.json",
      "url": "https://www.receptmuhely.hu/p/knorr-halaszlekocka.html/05996358014286",
      "gtin": "05996358014286",
      "checkedAt": "2026-03-12T06:55:07.653Z"
    },
    {
      "type": "problematic",
      "brand": "recipedia",
      "assortmentCode": "BF8813",
      "feedUrl": "https://www.receptmuhely.hu/home.productfeed.json",
      "url": "https://www.receptmuhely.hu/p/knorr-petrezselymes-tyukhusleveskocka.html/05996358019540",
      "gtin": "05996358019540",
      "checkedAt": "2026-03-12T06:58:41.522Z"
    },
    {
      "type": "problematic",
      "brand": "recipedia",
      "assortmentCode": "BF8813",
      "feedUrl": "https://www.receptmuhely.hu/home.productfeed.json",
      "url": "https://www.receptmuhely.hu/p/knorr-snack-teszta-carbonara.html/08584057005352",
      "gtin": "08584057005352",
      "checkedAt": "2026-03-12T06:53:33.625Z"
    },
    {
      "type": "problematic",
      "brand": "recipedia",
      "assortmentCode": "BF8813",
      "feedUrl": "https://www.receptmuhely.hu/home.productfeed.json",
      "url": "https://www.receptmuhely.hu/p/knorr-tejszines-paprikas-szosz.html/08710604746076",
      "gtin": "08710604746076",
      "checkedAt": "2026-03-12T06:58:41.524Z"
    },
    {
      "type": "problematic",
      "brand": "recipedia",
      "assortmentCode": "BF8813",
      "feedUrl": "https://www.receptmuhely.hu/home.productfeed.json",
      "url": "https://www.receptmuhely.hu/p/knorr-tejszines-gombas-szosz.html/08710604746199",
      "gtin": "08710604746199",
      "checkedAt": "2026-03-12T06:52:59.048Z"
    },
    {
      "type": "problematic",
      "brand": "recipedia",
      "assortmentCode": "BF8813",
      "feedUrl": "https://www.receptmuhely.hu/home.productfeed.json",
      "url": "https://www.receptmuhely.hu/p/knorr-teriyaki-szosz.html/08710908934759",
      "gtin": "08710908934759",
      "checkedAt": "2026-03-12T06:58:41.522Z"
    },
    {
      "type": "problematic",
      "brand": "recipedia",
      "assortmentCode": "BF8813",
      "feedUrl": "https://www.receptmuhely.hu/home.productfeed.json",
      "url": "https://www.receptmuhely.hu/p/knorr-bogres-gombakremleves-zsemlekockaval.html/08712100867569",
      "gtin": "08712100867569",
      "checkedAt": "2026-03-12T06:58:41.523Z"
    },
    {
      "type": "problematic",
      "brand": "recipedia",
      "assortmentCode": "BF8813",
      "feedUrl": "https://www.receptmuhely.hu/home.productfeed.json",
      "url": "https://www.receptmuhely.hu/p/knorr-bogres-csirkekremleves-zsemlekockaval.html/08712100867682",
      "gtin": "08712100867682",
      "checkedAt": "2026-03-12T06:54:52.887Z"
    },
    {
      "type": "problematic",
      "brand": "recipedia",
      "assortmentCode": "BF8813",
      "feedUrl": "https://www.receptmuhely.hu/home.productfeed.json",
      "url": "https://www.receptmuhely.hu/p/knorr-bogres-sajtkremleves-zsemlekockaval.html/08712100867743",
      "gtin": "08712100867743",
      "checkedAt": "2026-03-12T06:58:41.522Z"
    },
    {
      "type": "problematic",
      "brand": "recipedia",
      "assortmentCode": "BF8813",
      "feedUrl": "https://www.receptmuhely.hu/home.productfeed.json",
      "url": "https://www.receptmuhely.hu/p/knorr-bogres-brokkolikremleves-zsemlekockaval.html/08712100868467",
      "gtin": "08712100868467",
      "checkedAt": "2026-03-12T06:58:41.932Z"
    },
    {
      "type": "problematic",
      "brand": "recipedia",
      "assortmentCode": "BF8813",
      "feedUrl": "https://www.receptmuhely.hu/home.productfeed.json",
      "url": "https://www.receptmuhely.hu/p/knorr-szojaszosz.html/08712423034983",
      "gtin": "08712423034983",
      "checkedAt": "2026-03-12T06:52:59.045Z"
    },
    {
      "type": "problematic",
      "brand": "recipedia",
      "assortmentCode": "BF8813",
      "feedUrl": "https://www.receptmuhely.hu/home.productfeed.json",
      "url": "https://www.receptmuhely.hu/p/knorr-eroleveskocka.html/08712423038158",
      "gtin": "08712423038158",
      "checkedAt": "2026-03-12T06:54:35.525Z"
    },
    {
      "type": "problematic",
      "brand": "recipedia",
      "assortmentCode": "BF8813",
      "feedUrl": "https://www.receptmuhely.hu/home.productfeed.json",
      "url": "https://www.receptmuhely.hu/p/knorr-csirkehusleves-kocka.html/08714100884980",
      "gtin": "08714100884980",
      "checkedAt": "2026-03-12T06:54:43.067Z"
    },
    {
      "type": "problematic",
      "brand": "recipedia",
      "assortmentCode": "BF8813",
      "feedUrl": "https://www.receptmuhely.hu/home.productfeed.json",
      "url": "https://www.receptmuhely.hu/p/knorr-snack-teszta-mac-and-cheese-jalapeno.html/08720182396921",
      "gtin": "08720182396921",
      "checkedAt": "2026-03-12T06:54:35.528Z"
    },
    {
      "type": "problematic",
      "brand": "recipedia",
      "assortmentCode": "BF8813",
      "feedUrl": "https://www.receptmuhely.hu/home.productfeed.json",
      "url": "https://www.receptmuhely.hu/p/delikat-etelizesito-350g.html/08720182681355",
      "gtin": "08720182681355",
      "checkedAt": "2026-03-12T06:52:59.048Z"
    },
    {
      "type": "problematic",
      "brand": "recipedia",
      "assortmentCode": "BF8813",
      "feedUrl": "https://www.receptmuhely.hu/home.productfeed.json",
      "url": "https://www.receptmuhely.hu/p/globus-majonez-csaladi-meret.html/08720182739100",
      "gtin": "08720182739100",
      "checkedAt": "2026-03-12T06:54:43.071Z"
    },
    {
      "type": "problematic",
      "brand": "recipedia",
      "assortmentCode": "BF8813",
      "feedUrl": "https://www.receptmuhely.hu/home.productfeed.json",
      "url": "https://www.receptmuhely.hu/p/globus-mustar-250g.html/08720182792761",
      "gtin": "08720182792761",
      "checkedAt": "2026-03-12T06:58:23.930Z"
    },
    {
      "type": "problematic",
      "brand": "recipedia",
      "assortmentCode": "BF8813",
      "feedUrl": "https://www.receptmuhely.hu/home.productfeed.json",
      "url": "https://www.receptmuhely.hu/p/mustar.html/08720182793980",
      "gtin": "08720182793980",
      "checkedAt": "2026-03-12T06:58:41.522Z"
    },
    {
      "type": "problematic",
      "brand": "recipedia",
      "assortmentCode": "BF8813",
      "feedUrl": "https://www.receptmuhely.hu/home.productfeed.json",
      "url": "https://www.receptmuhely.hu/p/knorr-sajtos-instant-teszta.html/08720182897916",
      "gtin": "08720182897916",
      "checkedAt": "2026-03-12T06:54:20.677Z"
    },
    {
      "type": "problematic",
      "brand": "recipedia",
      "assortmentCode": "BF8813",
      "feedUrl": "https://www.receptmuhely.hu/home.productfeed.json",
      "url": "https://www.receptmuhely.hu/p/knorr-grizgaluskaleves.html/08720182975195",
      "gtin": "08720182975195",
      "checkedAt": "2026-03-12T06:53:58.329Z"
    },
    {
      "type": "problematic",
      "brand": "recipedia",
      "assortmentCode": "BF8813",
      "feedUrl": "https://www.receptmuhely.hu/home.productfeed.json",
      "url": "https://www.receptmuhely.hu/p/globus-light-majonez.html/08721201900969",
      "gtin": "08721201900969",
      "checkedAt": "2026-03-12T06:58:41.663Z"
    },
    {
      "type": "problematic",
      "brand": "recipedia",
      "assortmentCode": "BF8813",
      "feedUrl": "https://www.receptmuhely.hu/home.productfeed.json",
      "url": "https://www.receptmuhely.hu/p/delikat-etelizesito-csirkes-etelekhez-200g.html/08721201904165",
      "gtin": "08721201904165",
      "checkedAt": "2026-03-12T06:54:33.043Z"
    },
    {
      "type": "problematic",
      "brand": "recipedia",
      "assortmentCode": "BF8813",
      "feedUrl": "https://www.receptmuhely.hu/home.productfeed.json",
      "url": "https://www.receptmuhely.hu/p/knorr-snack-tesztas-keszetel-bolognai-szoszos.html/08721201919732",
      "gtin": "08721201919732",
      "checkedAt": "2026-03-12T06:55:02.719Z"
    },
    {
      "type": "problematic",
      "brand": "recipedia",
      "assortmentCode": "BF8813",
      "feedUrl": "https://www.receptmuhely.hu/home.productfeed.json",
      "url": "https://www.receptmuhely.hu/p/knorr-snack-tesztas-keszetel-ementali-szoszos.html/08721201920363",
      "gtin": "08721201920363",
      "checkedAt": "2026-03-12T06:53:58.328Z"
    },
    {
      "type": "problematic",
      "brand": "recipedia",
      "assortmentCode": "BF8813",
      "feedUrl": "https://www.receptmuhely.hu/home.productfeed.json",
      "url": "https://www.receptmuhely.hu/p/hellmanns-bbq-szosz.html/08721317701511",
      "gtin": "08721317701511",
      "checkedAt": "2026-03-12T06:55:10.230Z"
    },
    {
      "type": "problematic",
      "brand": "recipedia",
      "assortmentCode": "BF8813",
      "feedUrl": "https://www.receptmuhely.hu/home.productfeed.json",
      "url": "https://www.receptmuhely.hu/p/knorr-snack-teszta-csirkes-burrito-izesitessel.html/08721317773921",
      "gtin": "08721317773921",
      "checkedAt": "2026-03-12T06:54:13.222Z"
    },
    {
      "type": "problematic",
      "brand": "recipedia",
      "assortmentCode": "BF8813",
      "feedUrl": "https://www.receptmuhely.hu/home.productfeed.json",
      "url": "https://www.receptmuhely.hu/p/knorr-snack-teszta-edes-savanyu-izesitessel.html/08721317774164",
      "gtin": "08721317774164",
      "checkedAt": "2026-03-12T06:55:02.716Z"
    },
    {
      "type": "problematic",
      "brand": "recipedia",
      "assortmentCode": "BF8813",
      "feedUrl": "https://www.receptmuhely.hu/home.productfeed.json",
      "url": "https://www.receptmuhely.hu/p/hellmanns-chunky-burger-szosz.html/08721317797279",
      "gtin": "08721317797279",
      "checkedAt": "2026-03-12T06:53:36.212Z"
    }
  ]
}