{
  "generatedAt": "2026-03-12T09:20:29.327Z",
  "brand": "luxglobal",
  "assortmentCode": "BH0307",
  "feedUrl": "https://www.lux.com/in/home.productfeed.json",
  "totalUrlsChecked": 15,
  "problematicPagesFound": 0,
  "successfulPages": [
    {
      "type": "successful",
      "url": "https://www.lux.com/in/p/lux-lavender-&-vitamin-c-exfoliating-soap.html/08901030937866",
      "gtin": "08901030937866",
      "checkedAt": "2026-03-12T09:20:29.301Z"
    },
    {
      "type": "successful",
      "url": "https://www.lux.com/in/p/lux-rose-&-aloe-vera-body-scrub.html/08901030944680",
      "gtin": "08901030944680",
      "checkedAt": "2026-03-12T09:20:29.292Z"
    },
    {
      "type": "successful",
      "url": "https://www.lux.com/in/p/lux-flaw-less-glow-bathing-soap.html/08901030948237",
      "gtin": "08901030948237",
      "checkedAt": "2026-03-12T09:20:29.326Z"
    }
  ],
  "errors": 12,
  "duration": "7.34s",
  "speedMetrics": "2.04 URLs/second",
  "problematicPages": [],
  "errorPages": [
    {
      "type": "error",
      "url": "https://www.lux.com/in/p/creamy-perfection.html/08901030508219",
      "error": "request to https://bin.cartwire.co/services/hashlanginfobutton?brand_name=luxglobal&locale=en-in&brand_code=BH0307&gtin=08901030508219 failed, reason: ",
      "checkedAt": "2026-03-12T09:20:28.826Z"
    },
    {
      "type": "error",
      "url": "https://www.lux.com/in/p/fresh-splash.html/08901030509902",
      "error": "request to https://bin.cartwire.co/services/hashlanginfobutton?brand_name=luxglobal&locale=en-in&brand_code=BH0307&gtin=08901030509902 failed, reason: ",
      "checkedAt": "2026-03-12T09:20:26.444Z"
    },
    {
      "type": "error",
      "url": "https://www.lux.com/in/p/velvet-touch.html/08901030554636",
      "error": "request to https://bin.cartwire.co/services/hashlanginfobutton?brand_name=luxglobal&locale=en-in&brand_code=BH0307&gtin=08901030554636 failed, reason: ",
      "checkedAt": "2026-03-12T09:20:24.350Z"
    },
    {
      "type": "error",
      "url": "https://www.lux.com/in/p/soft-touch.html/08901030555480",
      "error": "request to https://bin.cartwire.co/services/hashlanginfobutton?brand_name=luxglobal&locale=en-in&brand_code=BH0307&gtin=08901030555480 failed, reason: ",
      "checkedAt": "2026-03-12T09:20:26.056Z"
    },
    {
      "type": "error",
      "url": "https://www.lux.com/in/p/lux-even-toned-glow-bathing-soap.html/08901030923708",
      "error": "request to https://bin.cartwire.co/services/hashlanginfobutton?brand_name=luxglobal&locale=en-in&brand_code=BH0307&gtin=08901030923708 failed, reason: ",
      "checkedAt": "2026-03-12T09:20:28.072Z"
    },
    {
      "type": "error",
      "url": "https://www.lux.com/in/p/lux-even-toned-glow-bathing-soap.html/08901030923746",
      "error": "request to https://bin.cartwire.co/services/hashlanginfobutton?brand_name=luxglobal&locale=en-in&brand_code=BH0307&gtin=08901030923746 failed, reason: ",
      "checkedAt": "2026-03-12T09:20:26.832Z"
    },
    {
      "type": "error",
      "url": "https://www.lux.com/in/p/lux-flaw-less-glow-bathing-soap.html/08901030929410",
      "error": "request to https://bin.cartwire.co/services/hashlanginfobutton?brand_name=luxglobal&locale=en-in&brand_code=BH0307&gtin=08901030929410 failed, reason: ",
      "checkedAt": "2026-03-12T09:20:29.205Z"
    },
    {
      "type": "error",
      "url": "https://www.lux.com/in/p/lux-flaw-less-glow-bathing-soap.html/08901030929427",
      "error": "request to https://bin.cartwire.co/services/hashlanginfobutton?brand_name=luxglobal&locale=en-in&brand_code=BH0307&gtin=08901030929427 failed, reason: ",
      "checkedAt": "2026-03-12T09:20:25.263Z"
    },
    {
      "type": "error",
      "url": "https://www.lux.com/in/p/lux-rose-&-aloe-vera-exfoliating-soap.html/08901030937859",
      "error": "request to https://bin.cartwire.co/services/hashlanginfobutton?brand_name=luxglobal&locale=en-in&brand_code=BH0307&gtin=08901030937859 failed, reason: ",
      "checkedAt": "2026-03-12T09:20:24.805Z"
    },
    {
      "type": "error",
      "url": "https://www.lux.com/in/p/lux-rose-&-aloe-vera-shimmering-bodywash.html/08901030937873",
      "error": "request to https://bin.cartwire.co/services/hashlanginfobutton?brand_name=luxglobal&locale=en-in&brand_code=BH0307&gtin=08901030937873 failed, reason: ",
      "checkedAt": "2026-03-12T09:20:25.670Z"
    },
    {
      "type": "error",
      "url": "https://www.lux.com/in/p/lux-lavender-&-vitamin-c-body-scrub.html/08901030944697",
      "error": "request to https://bin.cartwire.co/services/hashlanginfobutton?brand_name=luxglobal&locale=en-in&brand_code=BH0307&gtin=08901030944697 failed, reason: ",
      "checkedAt": "2026-03-12T09:20:29.204Z"
    },
    {
      "type": "error",
      "url": "https://www.lux.com/in/p/lux-fresh-glow-plus-bathing-soap.html/08901030970214",
      "error": "request to https://bin.cartwire.co/services/hashlanginfobutton?brand_name=luxglobal&locale=en-in&brand_code=BH0307&gtin=08901030970214 failed, reason: ",
      "checkedAt": "2026-03-12T09:20:29.204Z"
    }
  ]
}